[
  {
    "AssetType": 4,
    "itemname": "Rail_Strait_01",
    "desc": "Straight Rail",
    "prefab": "Rail_Strait_01",
    "purchasecost": 20,
    "maintcost": 30,
    "quality": 10,
    "maxspeed": 5,
    "qtyInStock": 0,
    "dangerContribution": 0,
    "connections": "NS"
  },
  {
    "AssetType": 4,
    "itemname": "Rail_LeftTurn_01",
    "desc": "Gentle Left Turn",
    "prefab": "Rail_LeftTurn_01",
    "purchasecost": 20,
    "maintcost": 22,
    "quality": 10,
    "maxspeed": 5,
    "qtyInStock": 0,
    "dangerContribution": 0,
    "connections": "SW"
  },
  {
    "AssetType": 4,
    "itemname": "Rail_RightTurn_01",
    "desc": "Gentle Right Turn",
    "prefab": "Rail_RightTurn_01",
    "purchasecost": 20,
    "maintcost": 26,
    "quality": 10,
    "maxspeed": 5,
    "qtyInStock": 0,
    "dangerContribution": 0,
    "connections": "ES"
  },
  {
    "AssetType": 3,
    "itemname": "ZhipperWheel",
    "desc": "ads",
    "prefab": "ZhipperWheelStill_02",
    "purchasecost": 123,
    "maintcost": 23,
    "quality": 0,
    "maxspeed": 0,
    "qtyInStock": 1,
    "dangerContribution": 0,
    "connections": ""
  },
  {
    "AssetType": 0,
    "itemname": "RailCar",
    "desc": "A little car for guests to ride in!",
    "prefab": "LowPolyCart_01",
    "purchasecost": 20,
    "maintcost": 5,
    "quality": 0,
    "maxspeed": 0,
    "qtyInStock": 0,
    "dangerContribution": 0,
    "connections": null
  },
  {
    "AssetType": 0,
    "itemname": "Paid Meeple",
    "desc": "A paid guest.",
    "prefab": "Meeple",
    "purchasecost": 5,
    "maintcost": 0,
    "quality": 0,
    "maxspeed": 0,
    "qtyInStock": 0,
    "dangerContribution": 0,
    "connections": null
  },
  {
    "AssetType": 2,
    "itemname": "Ticket booth",
    "desc": "Wheree else can they buy tickets??",
    "prefab": "TicketBooth",
    "purchasecost": 30,
    "maintcost": 10,
    "quality": 0,
    "maxspeed": 0,
    "qtyInStock": 0,
    "dangerContribution": 0,
    "connections": null
  },
  {
    "AssetType": 3,
    "itemname": "WaterSlideJump_01",
    "desc": "Slipery and Wet",
    "prefab": "WaterSlideJump_01",
    "purchasecost": 100,
    "maintcost": 20,
    "quality": 0,
    "maxspeed": 0,
    "qtyInStock": 0,
    "dangerContribution": 0,
    "connections": null
  },
  {
    "AssetType": 3,
    "itemname": "UpsideDown_01",
    "desc": "Vomit Comet",
    "prefab": "UpsideDown_01",
    "purchasecost": 300,
    "maintcost": 23,
    "quality": 0,
    "maxspeed": 0,
    "qtyInStock": 0,
    "dangerContribution": 0,
    "connections": null
  },
  {
    "AssetType": 3,
    "itemname": "Barfing ",
    "desc": "Barf Barf Barf",
    "prefab": "BarfingSwing_01",
    "purchasecost": 75,
    "maintcost": 10,
    "quality": 0,
    "maxspeed": 0,
    "qtyInStock": 0,
    "dangerContribution": 0,
    "connections": null
  },
  {
    "AssetType": 3,
    "itemname": "Pointy Pointy ",
    "desc": "Makes you drop",
    "prefab": "HelixDrop_01",
    "purchasecost": 175,
    "maintcost": 20,
    "quality": 0,
    "maxspeed": 0,
    "qtyInStock": 0,
    "dangerContribution": 12,
    "connections": null
  },
  {
    "AssetType": 3,
    "itemname": "Carousel",
    "desc": "No one over 30 years old allowed, ever!",
    "prefab": "Carousel",
    "purchasecost": 300,
    "maintcost": 20,
    "quality": 0,
    "maxspeed": 0,
    "qtyInStock": 0,
    "dangerContribution": 12,
    "connections": null
  },
  {
    "AssetType": 3,
    "itemname": "Brain Loop",
    "desc": "Messes with your head!",
    "prefab": "BrainScrambler_01",
    "purchasecost": 200,
    "maintcost": 20,
    "quality": 0,
    "maxspeed": 0,
    "qtyInStock": 0,
    "dangerContribution": 12,
    "connections": null
  },
  {
    "AssetType": 3,
    "itemname": "Portapotty",
    "desc": "Biohazards be warned",
    "prefab": "PortaPotty_01",
    "purchasecost": 200,
    "maintcost": 20,
    "quality": 0,
    "maxspeed": 0,
    "qtyInStock": 0,
    "dangerContribution": 12,
    "connections": null
  },
  {
    "AssetType": 3,
    "itemname": "Leap of Faith",
    "desc": "Watch your back",
    "prefab": "LeapOfFaith_01",
    "purchasecost": 200,
    "maintcost": 20,
    "quality": 0,
    "maxspeed": 0,
    "qtyInStock": 0,
    "dangerContribution": 12,
    "connections": null
  },
  {
    "AssetType": 2,
    "itemname": "Ambulance",
    "desc": "Your theme parks Private Medical Servicev",
    "prefab": "MedicalCar",
    "purchasecost": 100,
    "maintcost": 20,
    "quality": 0,
    "maxspeed": 0,
    "qtyInStock": 0,
    "dangerContribution": 0,
    "connections": null
  }
]